[
  {
    "id": 0,
    "actif": true,
    "fr": {
      "titre": "Bienvenue",
      "message": "Bienvenue sur Distill !"
    },
    "en": {
      "titre": "Welcome",
      "message": "Welcome to Distill !"
    }
  },
  {
    "id": 1,
    "actif": false,
    "fr": {
      "titre": "Nouveauté : Mode Sombre",
      "message": "Tes yeux vont nous remercier ! Le mode sombre est enfin disponible."
    },
    "en": {
      "titre": "New: Dark Mode",
      "message": "Your eyes will thank us! Dark mode is finally available."
    }
  },
  {
    "id": 2,
    "actif": false,
    "fr": {
      "titre": "Maintenance demain",
      "message": "Le serveur sera en pause café demain à 14h."
    },
    "en": {
      "titre": "Maintenance Tomorrow",
      "message": "The server will be on a coffee break tomorrow at 2 PM."
    }
  },
  {
    "id": 3,
    "actif": false,
    "fr": {
      "titre": "Alerte de sécurité",
      "message": "Attention ! Quelqu'un est en train de coder un super logiciel... Ah c'est toi."
    },
    "en": {
      "titre": "Security Alert",
      "message": "Warning! Someone is coding an awesome software... Oh wait, it's you."
    }
  },
  {
    "id": 4,
    "actif": false,
    "fr": {
      "titre": "Astuce : Raccourcis",
      "message": "Gagne du temps avec les raccourcis clavier dans le menu aide !"
    },
    "en": {
      "titre": "Tip: Shortcuts",
      "message": "Save time with keyboard shortcuts in the help menu!"
    }
  },
  {
    "id": 5,
    "actif": false,
    "fr": {
      "titre": "Bug corrigé",
      "message": "Le problème d'affichage sur les petits écrans est de l'histoire ancienne."
    },
    "en": {
      "titre": "Bug Fixed",
      "message": "The display issue on small screens is now history."
    }
  },
  {
    "id": 6,
    "actif": false,
    "fr": {
      "titre": "Communauté",
      "message": "Rejoins notre Discord pour partager tes créations avec Distill."
    },
    "en": {
      "titre": "Community",
      "message": "Join our Discord to share your creations with Distill."
    }
  },
  {
    "id": 7,
    "actif": false,
    "fr": {
      "titre": "Performance",
      "message": "L'application est maintenant 20% plus rapide au démarrage."
    },
    "en": {
      "titre": "Performance",
      "message": "The app is now 20% faster at startup."
    }
  },
  {
    "id": 8,
    "actif": false,
    "fr": {
      "titre": "Le saviez-vous ?",
      "message": "Tu peux glisser-déposer tes fichiers directement dans l'interface."
    },
    "en": {
      "titre": "Did you know?",
      "message": "You can drag and drop your files directly into the interface."
    }
  },
  {
    "id": 9,
    "actif": true,
    "fr": {
      "titre": "Fin du test",
      "message": "C'était la dixième notification. Tout fonctionne bien !"
    },
    "en": {
      "titre": "Test Finished",
      "message": "This was the tenth notification. Everything is working fine!"
    }
  }
]
